seriesheatmap/__init__.py
seriesheatmap/heatmap.py
seriesheatmap/models.py
seriesheatmap/scraper.py
seriesheatmap/serializer.py
seriesheatmap-0.0.4.dist-info/LICENSE
seriesheatmap-0.0.4.dist-info/METADATA
seriesheatmap-0.0.4.dist-info/WHEEL
seriesheatmap-0.0.4.dist-info/top_level.txt
seriesheatmap-0.0.4.dist-info/RECORD
