Metadata-Version: 2.1
Name: seriesheatmap
Version: 0.0.4
Summary: Scraper and heatmap plotter for episode ratings of series on IMDB
Author-email: Florian Trautweiler <florian.trautweiler@hispeed.ch>
License: MIT License
Project-URL: repository, https://github.com/trflorian/imdb-scraper-heatmap
Keywords: series,heatmap,scraper
Classifier: Programming Language :: Python :: 3
Classifier: License :: OSI Approved :: MIT License
Classifier: Operating System :: OS Independent
Requires-Python: >=3.7
License-File: LICENSE
Requires-Dist: pandas
Requires-Dist: selenium
Requires-Dist: lxml
Requires-Dist: numpy
Requires-Dist: matplotlib
Requires-Dist: tqdm
